{"location": {"country": "US", "locality": "Greater Seattle Area", "region": "Greater Seattle Area", "postal_code": "98109", "street_address": null, "latitude": 47.591396, "longitude": -122.33279}, "salary": {"currency": null, "min_value": null, "max_value": null, "unit": null}, "job": {"title": "Software Engineer", "industry": "", "description": "POSITION\n(REMOTE) Software Engineer \u2013 Web Apps\nCOMPANY OVERVIEW\nFounded in 2011, privately held TransformativeMed, Inc., headquartered in Seattle, Washington, is the world-wide leader in developing Cerner and Epic integrated solutions that enable hospitals and health systems to modernize their Electronic Health Record (EHR).\nOur mission is simple:\nMake clinician\u2019s lives easier and improve patient safety by simplifying the medical software experience through embedded applications and ancillary tools.\nPOSITION OVERVIEW\nTransformativeMed is seeking a mid or senior front-end leaning full-stack software engineer.\nThe primary focus of this position will be front-end development of the Core Diabetes App using JavaScript (jQuery/React) and other related web technologies. However, competency in middle-ware/back-end technologies is desired as occasional RESTful API work with PHP/Postgres will be needed.\nThis position will also have the opportunity to collaborate with our other development teams but will remain predominately focused on the Core Diabetes App to start.\nCOMPETENCIES & ESSENTIAL ATTRIBUTES\n\u00b7\u00a0\u00a0Ability and desire to work in a team setting, collaborating with product management, developers, customers and clinicians is expected\n\u00b7\u00a0\u00a0Proficient written and verbal communication skills\n\u00b7\u00a0\u00a0Thrive in a dynamic start-up environment\n\u00b7\u00a0\u00a0Eagerness to learn\n\u00b7\u00a0\u00a0Ability to work with a degree of technical ambiguity\nESSENTIAL FUNCTIONS\n\u00b7\u00a0\u00a0Refactor existing legacy jQuery application into new standardized React product\n\u00b7\u00a0\u00a0Improve existing features for legacy application versions\n\u00b7\u00a0\u00a0Provide detailed product documentation for your contributions\n\u00b7\u00a0\u00a0Collaborate with the Solutions Delivery team to deliver and support deployments for new and existing clients as needed with occasional after-hours tasks\n\u00b7\u00a0\u00a0Provide Tier-3 support for client-reported issues as needed\nREQUIRED SKILLS\n\u00b7\u00a0\u00a0Bachelor\u2019s degree or equivalent relevant work experience\n\u00b7\u00a0\u00a04+ years experience of front-end development with JavaScript\nHTML5\nCSS3\nJavaScript: jQuery and React, Angular or similar SPA Frameworks\nResponsive/Cross-Browser Web Design\nTemplating engines (MustacheJS/Handlebars)\n\u00b7\u00a0\u00a02+ years experience of back-end development\nPHP or NodeJS\nSQL\nApache or Nginx\n\u00b7\u00a0\u00a0Experience with industry standard development tools/practices\nGit and GitHub\nJSON/XML/WebSockets/SOAP/RESTful APIs\nVirtualization technology (Vagrant/Docker/VirtualBox/VMWare/KVM)\nWaterfall and Agile development methodologies\nKnowledge of common software development patterns\nBONUS SKILLS\n\u00b7\u00a0\u00a0Previous healthcare development experience with Cerner CCL, mPages, or PowerChart\n\u00b7\u00a0\u00a0Linux system administration and scripting (CentOS/RedHat/Bash)\n\u00b7\u00a0\u00a0CI/CD Pipeline configuration (Jenkins, Bamboo, GitHub CI)\n\u00b7\u00a0\u00a0Automated testing experience (WebDriver, Mocha, Protractor)\n\u00b7\u00a0\u00a0Knowledge of JavaScript transpilers/minifiers (Babel, Webpack, Typescript)\n\u00b7\u00a0\u00a0Cordova development\nSUPERVISORY RESPONSIBILITY\n\u00b7\u00a0\u00a0None\nPERFORMANCE & SUCCESS MEASURES\n\u00b7\u00a0\u00a0Growth in application/infrastructure knowledge for our product suite and related EHR application/infrastructure knowledge\n\u00b7\u00a0\u00a0Shippable development contributions to the core company products with minimal rework\n\u00b7\u00a0\u00a0Effective and timely technical support for complex issue escalation\n\u00b7\u00a0\u00a0Ability to work effectively and collaboratively with the TransformativeMed team\n\u00b7\u00a0\u00a0Consistent contributions to code/product documentation\nCOMPANY BENEFITS\n\u00b7\u00a0\u00a0Employee-centric culture, we consider and contribute to your career growth\n\u00b7\u00a0\u00a0Competitive pay\n\u00b7\u00a0\u00a0Unlimited PTO and flexible work schedules\n\u00b7\u00a0\u00a0Health/dental/vision/disability insurance\nOUR APPLICATIONS\nCore Mobile App\n\u2013 An iOS/Android application that presents rich, actionable EHR information in a format unique to each clinical specialty\u2019s priorities. Clinical teams caring for a patient have what they need, when they need it, can organize rounds, convey discharge readiness, conduct handoffs, and manage their patient lists. As status and situations change, smart notifications and secure messaging ensure the right information is provided to act.\nCore Work Manager App\n\u2013 An EHR-embedded application that can create any number of patient lists, group and filter them based on the team\u2019s specialty or individual\u2019s needs, and view data in their preferred format. Built-in capabilities securely synchronize tasks; route alerts, notifications, and secure messages across the entire care team.\nCore Diabetes App\n\u2013 An EHR-embedded application that standardizes and streamlines the management of patients with diabetes, ensuring patient safety from admission to discharge. By presenting workflow wizards, visualizing important clinical data, and providing a comprehensive dashboard of diabetic patients, the Core Diabetes App helps clinicians effectively and quickly treat diabetic conditions.\nEqual Opportunity Employer\nTransformativeMed is an equal opportunity employer and is committed to diversity and inclusion in the workplace. We prohibit discrimination and harassment of any kind based on race, color, sex, religion, sexual orientation, national origin, disability, genetic information, pregnancy, or any other protected characteristic as outlined by federal, state, or local laws.\nThis policy applies to all employment practices within our organization, including hiring, recruiting, promotion, termination, layoff, recall, leave of absence, compensation, benefits, training, and apprenticeship. TransformativeMed makes hiring decisions based solely on qualifications, merit, and business needs at the time.\nOther Duties\nPlease note this job description is not designed to cover or contain a comprehensive listing of activities, duties or responsibilities that are required of the employee for this job. Duties, responsibilities, and activities may change at any time with or without notice.", "employment_type": "FULL_TIME", "date_posted": "2021-07-14T17:20:56.000Z"}, "company": {"name": "TransformativeMed", "link": "https://www.linkedin.com/company/transformativemed"}, "education": {"required_credential": "bachelor degree"}, "experience": {"months_of_experience": 48, "seniority_level": "Mid-Level"}}