{
  "job": {
    "title": "Site Reliability Engineer",
    "industry": "Information Technology and Services",
    "description": "ltpgtskyepoint decisions inc is seeking a highly motivated teamoriented individual to fill the role ofampnbspltstronggtsite reliability engineerampnbspltstronggtthe site reliability engineer will support the devsecops teams test environment and data engineering with the automation ondemand creation and the provisioning and breakdown of test environments and databases the leveraging of existing and innovative technology solutions to automate data seeding and test data management and ensuring that the integrated test lab itl environment adequately supports testing activities included in this acquisition devsecops engineering establishment of best practices in devsecops provision of devsecops engineering services for the uscis oit programs to facilitate agile and devsecops best practices and innovative solutions security testing and engineering identification of the threats and the measures of potential vulnerabilities in systems applications and services in a highlyintegrated environment comprised of various tools technology and cicd pipelinesltpgtltpgtltbrgtltpgtltpgtltstronggtltspan classqlcursorgtltspangtresponsibilitiesltstronggtltpgtltulgtltligtdevelops automated provisioning and deployment capabilities with testing environments and databasesltligtltligtestablishes and maintains the automated build and teardown of test environments based on testing demandltligtltulgtltpgtltstronggtqualificationsltstronggtltpgtltulgtltligtmust be a us citizen and able to obtain a dhs public trust clearanceltligtltligtbachelors degree and five years of experienceltligtltulgtltpgtltbrgtltpgtltpgtltemgtskyepoint decisions is a leading cybersecurity architecture and engineering critical infrastructure and operations and applications development and maintenance it service provider headquartered in dulles virginia with operations across the us we provide innovative enterprisewide solutions as well as targeted services addressing the complex challenges faced by our federal government clients our focus is on enabling our clients to most efficiently and effectively deliver their mission anytime anywhere securely we combine technical expertise mission awareness and an empowered workforce to produce meaningful resultsltemgtltpgtltpgtltstronggtampnbspltstronggtltpgtltpgtltemgtskyepoint decisions is an established iso and isoiec certified small business and appraised at cmmi level with sam for services we possess a common vision of excellence and foster a collaborative team culture built upon individual performance and accountability we invest in our people and systems to create value for our clients it is the skyepoint way we are grateful for the opportunity to work with exceptional people and give back to the communities we serveltemgtltpgtltpgtltstronggtampnbspltstronggtltpgtltpgtltemgtskyepoint decisions is committed to hiring and retaining a diverse workforce we are an equal opportunity employer making decisions without regard to race color religion sex national origin age veteran status disability or any other protected class us citizenship is required for most positionsltemgtltpgt",
    "employment_type": "FULL_TIME",
    "date_posted": "2021-08-06T17:39:49.000Z"
  },
  "company": {
    "name": "SkyePoint Decisions, Inc.",
    "link": "https://www.linkedin.com/company/skyepoint-decisions-inc-"
  },
  "education": {
    "required_credential": "bachelor degree"
  },
  "experience": {
    "months_of_experience": 60,
    "seniority_level": ""
  },
  "salary": {
    "currency": "",
    "min_value": "",
    "max_value": "",
    "unit": ""
  },
  "location": {
    "country": "US",
    "locality": "Washington DC-Baltimore Area",
    "region": null,
    "postal_code": "21201",
    "street_address": null,
    "latitude": 38.873062,
    "longitude": -77.007385
  }
}