{"location": {"country": "US", "locality": "San Jose", "region": "San Jose", "postal_code": "95148", "street_address": null, "latitude": 37.334793, "longitude": -121.888145}, "salary": {"currency": null, "min_value": null, "max_value": null, "unit": null}, "job": {"title": "Corporate Recruiter", "industry": "Internet", "description": "Whatfix is looking for a stellar\nCorporate Recruiter\nto join our Talent Acquisition team in North America.\u00a0 We are growing quickly, and our hiring in North America is set to grow exponentially.\nWho are we?\nWhatfix is the #1 Digital Adoption Platform (DAP) for Enterprises. We are changing the way Enterprises train and support their end-users on Applications. We provide companies with a SaaS platform that accelerates their employees' learning of new applications, by giving them guided tutorials in the application.\u00a0 The platform also provides continuous on-demand support for end-users, again within the application, in a guided manner.\nThe product helps to accelerate product adoption, and is redefining the way companies onboard, train, and provide support to users. Over 100 Fortune 1000 enterprises worldwide trust Whatfix to reduce the time-to-value of business applications and improve users productivity and performance.\nWe are looking for exceptionally talented and motivated individuals to help us build the world\u2019s best software at scale for thousands of clients. Join us as we reinvent the product adoption cycle.\nWhat sets us apart from the rest?\n$140million in funding, most recently a $90mm Series D from investors like Sequoia Capital, SoftBank, Stellaris, Cisco, and Eight Roads\nWith over 100 of the Fortune 1000 already onboard as customers, Whatfix has been named among the top 20 B2B tech companies alongside the likes of Adobe, PayPal, and Cisco\nWhatfix is on pace to grow over 100% this year: Our most recent quarters had exponential sales growth - Q1 \u201821 had 2.4x the sales from Q1 \u201820 and Q2 \u201821 had 2.6x the sales from Q2 \u201820\nGartner and Everest Research recognize Whatfix as a Global Market Leader in the digital adoption space\nCustomer rating of 4.7+ on platforms like G2 Crowd & Gartner Peer Insights\n\u201cHustle Mode ON\u201d is something we live by.\nAbout the Role\nWhatfix is growing quickly, and as a result, we are looking to grow our talent acquisition team in North America.\nReporting to the Lead Go-to-Market Recruiter, the Corporate Recruiter will work closely with the leaders of our GTM functions, such as Marketing, Sales & Business Development, Account Management, Sales Engineering and Customer Success to build recruiting strategies and execute upon them.\u00a0You should be comfortable operating as a full-cycle individual contributor, from sourcing to offer negotiation.\nDuties and Responsibilities:\nPartner with hiring managers, business unit heads, and HR/TA team to recruit and hire the best talent in market\nManage the full-cycle recruiting process for specific GTM roles in North America\nCollaborate with Hiring Managers across departments like Marketing, Account Management, Sales & Business Development, Sales Engineering, and Customer Success to define role requirements, interview processes, hiring criteria, and to negotiate offers\nCreate unique and robust search strategies to identify and attract the best talent\nDevelop innovative ways to raise the bar on how Whatfix recruits talent\nLead calibration sessions with hiring managers and business unit leaders during the interview process, incorporating feedback into the search on an interactive basis\nBalance providing a high touch experience throughout the entire recruiting process with both internal stakeholders and candidates, while continuously keeping the pipeline active and meeting your hiring goals\nUse data and metrics reporting to drive continuous process and strategy improvement\nCollaborate in the development of strategies that influence and attract the right talent to join Whatfix at the right time\nQualifications\n3+ years of experience recruiting best-in-market talent for a fast-paced, high growth technology company\nPrevious experience recruiting for Sales, Partnership, Customer Success, Marketing, Tech roles and related functions is highly preferred\nStrong stakeholder management skills - ability to manage competing priorities across different hiring levels\nAbility to prioritize between multiple jobs and competing priorities\nStrong client focus and commitment to continuous improvement\nStrong research skills\nSelf-directed and proactive\nHigh Emotional Quotient (EQ) and ability to navigate nuance\nAbility to execute innovative sourcing strategies\nAbility to learn and leverage stellar negotiation skills\nProven track record and success recruiting in a technology product company\nModel the behaviors of a true team player and be a guardian of the Whatfix culture\nDetail-oriented and comfortable using applicant tracking systems like Recruiterbox\nAbility to find humor in the most mundane days\nBS/BA degree preferred\nExperience recruiting within the Enterprise Software sector preferred\nIndustry knowledge in Software, Web 2.0, SaaS / Cloud, Startups, etc. is preferred\nPerks / Benefits\nUnlimited PTO policy\nMedical, Dental, and Vision coverage\n401 K Plan\nFree parking onsite\nWe are an equal opportunity employer and value diversity at our company. We do not discriminate on the basis of race, religion, color, national origin, gender, sexual orientation, age, marital status, veteran status, or disability status.", "employment_type": "FULL_TIME", "date_posted": "2021-08-25T17:24:32.000Z"}, "company": {"name": "Whatfix", "link": "https://www.linkedin.com/company/whatfix"}, "education": {"required_credential": "bachelor degree"}, "experience": {"months_of_experience": 36, "seniority_level": "Mid-Level"}}