{
  "job": {
    "title": "Software Engineer",
    "industry": "Marketing and Advertising",
    "description": "ltpgtltstronggtltugtresponsibilitiesltugtltstronggtltpgtltulgtltligtunderstands that testing and coding go hand in handltligtltligtsolves problems with solid reusable components built on well known patternsltligtltligthas the ability to produce clean dry code on aggressive timelinesltligtltligtcan mentor other team members and show them the path to clean dry codeltligtltligtbelieves that good code metrics are not just interesting goals but requirementsltligtltligtpossesses strong gitfultligtltulgtltpgtampnbspltpgtltpgtltstronggtltugtrequirementsltugtltstronggt ltpgtltulgtltligtcomputer science degree or relatedltligtltligthas experience with java spring framework and javascriptltligtltligthas experience with mysql postgres or equivalent rdbmsltligtltligtexperience with mapreduce programming and hadoop is preferredltligtltligtexperience working in amazon web services is preferredltligtltligtexperience with containerization is preferredltligtltulgtltpgtltpgt",
    "employment_type": "FULL_TIME",
    "date_posted": "2021-07-14T17:16:18.000Z"
  },
  "company": {
    "name": "Cypress HCM",
    "link": "https://www.linkedin.com/company/cypress-hcm"
  },
  "education": {
    "required_credential": "bachelor degree"
  },
  "experience": {
    "months_of_experience": "",
    "seniority_level": ""
  },
  "salary": {
    "currency": "",
    "min_value": "",
    "max_value": "",
    "unit": ""
  },
  "location": {
    "country": "US",
    "locality": "Lisle",
    "region": "IL",
    "postal_code": "60532",
    "street_address": null,
    "latitude": 41.80125,
    "longitude": -88.07478
  }
}