{
  "job": {
    "title": "Technical Associate",
    "industry": "Semiconductors",
    "description": "ltpgtltemgtspectraphysics ophir and newport are brands within the mks instruments light ampamp motion division we provide a full range of solutions including lasers for precision industrial and scientific research applications laser and led measurement beam profiling precision motion control optical tables and vibration isolation systems photonics instruments optomechanical components and optical elements mks light ampamp motion solutions enhance our customers capabilities and productivity in the semiconductor industrial technologies life and health sciences research and defense marketsltemgtltpgtltpgtltbrgtltpgtltpgtare you naturally curious so are we at mks our collective curiosity drives us to be an innovation leader in many industries our products drive technology advancements across a wide range of applications such as g augmentedvirtual reality autonomous vehicles clean drinking water and space exploration we are a team of collaborators who value fresh thinking and believe in mutual respect constructive candor diversity and inclusion as a valued and trusted partner to our customers we are continually pushing the boundaries of possibility we believe in creating technology that transforms our world and are looking for likeminded individuals to join our team if this is appealing to you we want to meet youltpgtltpgtltbrgtltpgtltpgtwe are looking for a ltstronggttechnical associateltstronggt to support manufacturing engineering for optical fabricationampnbsp this will be a handson role immersed in day to day operations and will routinely use a variety of manufacturing equipmentampnbsp in this role you willltpgtltulgtltligtperform functions associated with all manufacturing operations including working with engineers in setup and calibration tasks as well as performing rework and quality testing related to the production of parts components subassemblies and final assembliesltligtltligtuse programs to collect and evaluate operating data to conduct online adjustments to products instruments or equipmentltligtltligtdetermine and may assist in developing methods and procedures to control or modify the manufacturing processltligtltligtwork with engineers in conducting experimentsltligtltligtassist in the development setup and documentation needed for fixturesltligtltligtassist in the support of new and existing products including preparing and maintaining work instructions ordering materials and providing basic manufacturing engineering supportltligtltulgtltpgtltbrgtltpgtltpgtwhat will you bring to the team along with your passion for optical fabrication isltpgtltulgtltligt year of optics industry experienceampnbsp knowledge of optical metrology techniques and specifications is preferredltligtltligthandson experience with optics and optics fabrication methodsltligtltligtability to read mechanical and assembly drawingsltligtltligtexperience supporting new product development is preferredltligtltligtlean manufacturing is preferredltligtltligtintermediate knowledge of standard software used for reports and documentation word excel powerpointltligtltulgtltpgtltbrgtltpgtltpgtltemgtmks instruments inc is an affirmative action and equal opportunity employer we solicit and hire applicants regardless of race color national origin sex religion age disability veteran status sexual orientation gender identity or any other protected category our policy is to employ the most qualified applicants we conduct background checks and drug screens in accordance with company policies and federal and state guidelinesltemgtltpgtltpgtltbrgtltpgtltpgtltemgtglobally our policy is to recruit individuals from wide and diverse backgroundsampnbsphowever certain positions require access to controlled goods and technologies subject to the international traffic in arms regulations itar or export administration regulations earampnbspapplicants for these positions may need to be us personsampnbspus persons are generally defined as us citizens noncitizen nationals lawful permanent residents or green card holders individuals granted asylum and individuals admitted as refugeesltemgtltpgtltpgtltbrgtltpgtltpgtltemgtmks instruments inc is an equal opportunity employer we solicit and hire applicants regardless of race color national origin sex religion age disability veteran status sexual orientation gender identity or any other protected category our policy is to employ the most qualified applicants we conduct background checks and drug screens in accordance with company policies and federal and state guidelinesltemgtltpgt",
    "employment_type": "FULL_TIME",
    "date_posted": "2021-08-18T22:06:21.000Z"
  },
  "company": {
    "name": "MKS Instruments",
    "link": "https://www.linkedin.com/company/mks-instruments"
  },
  "education": {
    "required_credential": ""
  },
  "experience": {
    "months_of_experience": 36,
    "seniority_level": ""
  },
  "salary": {
    "currency": "",
    "min_value": "",
    "max_value": "",
    "unit": ""
  },
  "location": {
    "country": "US",
    "locality": "Irvine",
    "region": "CA",
    "postal_code": "92717",
    "street_address": null,
    "latitude": 33.68591,
    "longitude": -117.82472
  }
}