{
    "job": {
        "title": "Senior Software Engineer",
        "industry": "Information Technology and Services",
        "description": "Our healthcare client is looking for a Senior Software Engineer to join their team! The Project: Working on a service layer that converts native API mostly built in JSON format to a HL7 FHIR API to interconnect health systems.Your Background: Experience developing software with Java. FHIR knowledge is a plusJob Responsibilities:Serve as a senior software developer for the software platform developing FHIR-based REST APIs.Allocated time, on average:75% of the time coding25% of the time collaborating with solution architects/BA/QA on overall software implantation design and best practicesProvide input on software solution designsWork across all teams as a subject matter expectMentor junior software developers on coding designs and best practicesRequired Skills:6+ years of experience with hands on development with C# or Java8+ years of experience dev2+ years of experience EHR clinical integrations2+ years of experience with integrating services into a cloud architecture2+ years of experience working with Docker containersExperience working in Agile environmentWe cannot provide sponsorship upon conversionWhat skills/attributes are preferred (will set a candidate apart)?2+ years of experience with good understanding on FHIR standard2+ years of experience developing RESTFUL APIsThe ability to execute existing queries as well as write SQL queries of varying complexityExperience with GIT for code repositoryExperience with Jenkins for deployment automationUnderstanding of software development processes and methodologiesCollaborate in team environment",
        "employment_type": "CONTRACTOR",
        "date_posted": "2021-08-25T17:37:32.000Z"
    },
    "company": {
        "name": "Apex Systems",
        "link": "https://www.linkedin.com/company/apex-systems"
    },
    "education": {
        "required_credential": "bachelor degree"
    },
    "experience": {
        "months_of_experience": 96,
        "seniority_level": ""
    },
    "salary": {
        "currency": "",
        "min_value": "",
        "max_value": "",
        "unit": ""
    },
    "location": {
        "country": "US",
        "locality": "Raleigh",
        "region": "NC",
        "postal_code": "27699",
        "street_address": null,
        "latitude": 35.781303,
        "longitude": -78.64168
    }
}