{"location": {"country": "US", "locality": "New York City Metropolitan Area", "region": "New York City Metropolitan Area", "postal_code": "10021", "street_address": null, "latitude": 40.748295, "longitude": -73.98556}, "salary": {"currency": null, "min_value": null, "max_value": null, "unit": null}, "job": {"title": "Software Engineer", "industry": "", "description": "EarlyBird Overview\nEarlyBird is the simplest way for parents, family, and friends to collectively invest in a child\u2019s financial future starting at the earliest age. Our focus is transforming financial gifting, making it personal, purposeful, and timeless, empowering future generations with financial freedom and the ability to change the world.\nIndustry\nFinancial Technology\nRobo-Advising\nJob Description\n2 - 5 years industry experience\nRequirements & Technologies\nAs a Software Developer at EarlyBird, you will have worked on projects that involve authentication, database design, and API integrations. Ideal candidates are comfortable touching various parts of a distributed system, as well as having intuition and opinions on how to improve and simplify a growing application.\nBuild and promote high-quality, scalable, full-stack solutions in React Native\nExperience with iOS and Android React Native applications\nDelight a diverse, global audience with elegant, intuitive experiences\n1-5 years of industry NodeJS experience in full time or internship roles\nGraphQL and REST API's development experience\nExperience with SQL databases\nSome quantitative skills, knowledge or experience in finance is a plus\nYou are a self-starter, self-motivated, and able to work independently\nSalary, Compensation, and Benefits\nCompetitive compensation that includes equity\nFlexible time off policy to balance your work and life\nCompetitive medical, dental, and vision coverage for you and your dependents\nCollaborative, transparent, and fun loving office culture\nAn impactful organization with a purpose\nAbility to work from home and have flexible working hours.\nPlease apply if you're excited about building a better financial future for the next generation and pushing our platform further. We look forward to seeing the unique perspective you will bring to our team!\nEarlyBird is an equal opportunity employer and values diversity at our company. We do not discriminate on the basis of race, religion, color, national origin, gender, sexual orientation, age, marital status, veteran status, or disability status.", "employment_type": "FULL_TIME", "date_posted": "2021-07-18T14:03:58.000Z"}, "company": {"name": "EarlyBird", "link": "https://www.linkedin.com/company/getearlybird"}, "education": {"required_credential": "bachelor degree"}, "experience": {"months_of_experience": 24, "seniority_level": "Mid-Level"}}