{
    "job": {
        "title": "Software Engineer",
        "industry": "Staffing and Recruiting",
        "description": "Designation/Position NameSoftware EngineerNumber of Vacancies1Client Name Johnson & Johnson Services, IncMode of Hire (TP/FTE/Either)TPCustomer Interview Required (Yes/No)YesJob Title Associate/ContractorJob Description(Define At least 6 points which candidate is supposed to do)Experience: 3 to 5yrsFamiliar with J&J Vision productsNeed to work with systems group, perform calibration, run work flows, measure if any signalsGo through systems error logs and should be able to understand issuesEmbedded systems understanding including SW, HW and FWShould be quick learner and flexible in workingKey Skills And Competencies RequiredActively participate among cross-functional teams to ensure projects are delivered on time and to required quality standards.Strong analytical and problem-solving skillsAbility to organize, plan and execute multiple tasks to tight schedulesHighly motivated self-starterAbility to document own work clearly and preciselyExcellent communication skillsEducation And ExperienceBachelor Degree in Engineering, Computer Science or equivalent degreePositions based at (Client location with Zip code)Johnson and Johnson Vision 510 Cottonwood Dr, Milpitas, CA 95035Work Authorization (Citizen/GC/H1B/Either)EitherMandatory SkillsTechnical / Soft SkillsExpertise Level (Expert / Good / Knowledge)RemarksC++GoodEmbedded KnowledgeGoodCommunication skillsGoodSDLCGoodThanks & Have a great Day.Akash KumarTechnical RecruiterSoftHQ IncConsulting Development StaffingCell Phone: (858) 381-9275Office Desk: 858-295-4434 x 6539:30 AM 5:30 PM (EST) | Mon - FriE-mail: k.akash@softhq.comWebsite: http://www.softhq.com",
        "employment_type": "FULL_TIME",
        "date_posted": "2021-09-12T03:52:54.000Z"
    },
    "company": {
        "name": "SoftHQ Inc",
        "link": "https://www.linkedin.com/company/softhq-inc"
    },
    "education": {
        "required_credential": "bachelor degree"
    },
    "experience": {
        "months_of_experience": "",
        "seniority_level": ""
    },
    "salary": {
        "currency": "",
        "min_value": "",
        "max_value": "",
        "unit": ""
    },
    "location": {
        "country": "US",
        "locality": "California",
        "region": "United States",
        "postal_code": "93266",
        "street_address": null,
        "latitude": 37.254673,
        "longitude": -119.61728
    }
}