{
  "job": {
    "title": "AWS Data Engineer",
    "industry": "Information Technology and Services,Computer &amp; Network Security,Information Services",
    "description": "ltpgtltstronggtaws data developerltstronggtltpgtltpgtltstronggtlocation mclean va fortune clientltstronggtltpgtltpgtltstronggtltugt days onsite after pandemicltugtltstronggtltpgtltpgtltstronggt months contractltstronggtltpgtltpgtltbrgtltpgtltpgtltstronggtltugtaws data developerltugtltstronggtltpgtltulgtltligtwe are migrating the legacy based platform into cloud solution hadoop to aws migration refactoring the compute into aws where we have kubernetes container based solutionsltligtltligt years of experience in software development including design coding testing and supportltligtltligt years of cloud infrastructure experience working with one or more of the following amazon web services aws cloud services ec emr ecs s sns sqs cloud formation cloud watch lambdaltligtltligthandson experiences with python and pysparkltligtltulgtltolgtltligthadoop and aws must have handson experience with development not administrationampnbspltligtltligtpython is a must have with sparkpysparkampnbspltligtltligtkubernetes knowledge is nice to haveltligtltolgt",
    "employment_type": "CONTRACTOR",
    "date_posted": "2021-10-05T17:31:26.000Z"
  },
  "company": {
    "name": "Technology Ventures",
    "link": "https://www.linkedin.com/company/technology-ventures"
  },
  "education": {
    "required_credential": "bachelor degree"
  },
  "experience": {
    "months_of_experience": 60,
    "seniority_level": ""
  },
  "salary": {
    "currency": "",
    "min_value": "",
    "max_value": "",
    "unit": ""
  },
  "location": {
    "country": "US",
    "locality": "McLean",
    "region": "VA",
    "postal_code": "22101",
    "street_address": null,
    "latitude": 38.93759,
    "longitude": -77.18378
  }
}