{
  "job": {
    "title": "Data Analyst",
    "industry": "Health, Wellness and Fitness",
    "description": "descriptionltbrgtltpgtltbrgtltbrgtltbrgtltpgtltpgtrelatient is a leading provider of integrated messaging solutions for practices hospitals and health care systems we take a patientcentered approach to engagement utilizing the power of realtime clinical data to deliver timely messages between patients and their care providers our platform effortlessly automates appointment reminders patient billing and payment collection satisfaction surveys selfscheduling checkin chat and ondemand messaging we are looking for talented people to join our team building platform solutions that integrate with enterprise health care systemsltbrgtltbrgt ltbrgtltbrgtltpgtltpgtltstronggtresponsibilitiesltbrgtltbrgtltstronggtltpgtltpgt work with product engineering and business resources to create and maintain analytics related to our products work with business stakeholders to identify business objectives measurement criteria kpi and operational reporting necessary to support our products and business functionsltbrgtltbrgt ltbrgtltbrgtltpgtltpgt identify analyze and interpret trends and patterns in complex data produce visual results in a meaningful easytounderstand way presenting results in dashboard reports and other presentation formats to our usersltbrgtltbrgt ltbrgtltbrgtltpgtltpgt identify data sources evaluate data types and validity perform the necessary etl data aggregation to provide the necessary data used to drive reporting and analysis for internal staff and our clients while producing industryleading automated and onetime visualizations and raw data reportingltbrgtltbrgt ltbrgtltbrgtltpgtltpgt oversee our production reporting platform ensure standards and maintained provide management and training as needed for users maintain a standard library of reporting that supports the business including standard weekly and oneoff reporting and analysisltbrgtltbrgtltpgtltulgtltligtmanage business intelligence platforms to enable technical and business usersltligtltulgtltpgtltstronggtrequirementsltbrgtltbrgtltstronggtltpgtltpgt exceptional interpersonal communication skills written and verbal active listening attention to detail critical thinking problemsolving and time management skillsltbrgtstrong analytic skills with expertise in data mining statistical analysis data analysis and evaluation of results with the ability to produce complex visualizations for the businessltbrgtltbrgtltpgtltulgtltligtstrong knowledge of and experience with databases mysql postrgresql and crm tools salesforceltligtltligtstrong knowledge of business intelligence platforms tableau powerbi looker etcltligtltligtknowledge of statistics and experience using statistical packages for analyzing datasets excel spss sas etcltligtltligtstrong analytical skills with the ability to collect organize analyze and disseminate significant amounts of information with attention to detail and accuracyltligtltligtadept at queries report writing and presenting findings familiarity with software languages and sql understanding of relational databases ability to reviewunderstand code and write complex sql select statementsltbrgtltbrgt ltligtltulgtltpgt a bachelorampaposs degree in mathematics economics computer science information management or statistics or relevant work equivalent with years experience focused on product or process definition and release processes experience working in a growth phase technology company particularly in healthcare a plusltbrgtltbrgt ltbrgtltbrgtltpgtltpgtltstronggtcompany overviewltbrgtltbrgtltstronggtltpgtltpgt the relatient offices are in franklin tn preferred or cookeville tn this position will be based in the franklin office with some travel to the cookeville officeltbrgtltbrgtltpgtltpgt you will be using the latest tools and technology solving realworld problems while working with large data sets complex backend data transformation rd party api integrations and multiple communication methods delivered natively through web text and voice mailltbrgtltbrgtltbrgtltbrgt ltbrgtltbrgtltpgtltbrgtltbrgtrequirementsltbrgtltpgtltstronggtabout relatientltbrgtltbrgtltstronggtltpgtltpgtltbrgtltbrgtltbrgtltpgtltpgtfounded in our offices are located in historic franklin and cookeville tn and include a casual dynamic work environment with a spirit of innovation and growthltbrgtltbrgtltpgtltpgtltbrgtltbrgtltbrgtltpgtltpgtour team consists of smart driven and creative people who are motivated to impact the way in which healthcare providers engage with their patients our platform takes a patientcentered approach to engagement utilizing the power of realtime clinical data to deliver timely messages between patients and their care providers our platform effortlessly automates appointment reminders patient billing and payment collection satisfaction surveys selfcheckin nonmedical transportation and on demand messagingltbrgtltbrgtltpgtltpgtltbrgtltbrgtltbrgtltpgtltpgtltbrgtltbrgtltbrgtltpgtltpgtltstronggtwhat we offerltbrgtltbrgtltstronggtltpgtltulgtltligtbase salary plus incentivesltligtltligtmedical dental and vision insuranceltligtltligtemployer hsa match contributionltligtltligtemployer paid life insuranceltligtltligt employer paid longterm disability insuranceltligtltligtkgenerous pto policy which includes weeks paid time off plus all paid holidaysltligtltligtperks such as an annual employee awards banquet holiday parties monthly lunches bottomless snacks and coffeeltligtltligtcasual culture with approachable leadershipltligtltligtgreat office environments located in historic franklin tn and beautiful cookeville tnltligtltulgtltpgtlearn more about our company at wwwrelatientnetltbrgtltbrgtltpgtltpgtltbrgtltbrgtltbrgtltpgtltpgtltbrgtltbrgtltbrgtltpgtltemgtltstronggtrelatient is an equal employment opportunity employerltbrgtltbrgtltstronggtltemgt",
    "employment_type": "FULL_TIME",
    "date_posted": "2021-10-18T06:04:34.000Z"
  },
  "company": {
    "name": "Relatient",
    "link": "https://www.linkedin.com/company/relatient"
  },
  "education": {
    "required_credential": "bachelor degree"
  },
  "experience": {
    "months_of_experience": 60,
    "seniority_level": ""
  },
  "salary": {
    "currency": "",
    "min_value": "",
    "max_value": "",
    "unit": ""
  },
  "location": {
    "country": "US",
    "locality": "Franklin",
    "region": "TN",
    "postal_code": "37064",
    "street_address": null,
    "latitude": 35.923653,
    "longitude": -86.86783
  }
}